[
  {
    "id": "mote",
    "title": "Mote",
    "hp": 35,
    "lifetime": 10.0,
    "drain_multiplier": 0.8,
    "speed": 160.0,
    "behavior_type": "skitter",
    "sprite_scale": 0.18,
    "sprite_tint": [0.45, 0.95, 1.0, 1.0],
    "collision_radius": 14.0,
    "idle_time_range": [0.15, 0.45],
    "walk_time_range": [0.1, 0.22]
  },
  {
    "id": "drifter",
    "title": "Drifter",
    "hp": 70,
    "lifetime": 14.0,
    "drain_multiplier": 1.2,
    "speed": 110.0,
    "behavior_type": "wander",
    "sprite_scale": 0.32,
    "sprite_tint": [0.82, 0.84, 0.9, 1.0],
    "collision_radius": 26.0,
    "idle_time_range": [0.8, 1.7],
    "walk_time_range": [0.3, 0.6]
  },
  {
    "id": "bulwark",
    "title": "Bulwark",
    "hp": 160,
    "lifetime": 20.0,
    "drain_multiplier": 1.8,
    "speed": 65.0,
    "behavior_type": "lumber",
    "sprite_scale": 0.52,
    "sprite_tint": [0.86, 0.32, 0.28, 1.0],
    "collision_radius": 40.0,
    "idle_time_range": [1.4, 2.6],
    "walk_time_range": [0.8, 1.4]
  },
  {
    "id": "leech",
    "title": "Leech",
    "hp": 90,
    "lifetime": 18.0,
    "drain_multiplier": 2.5,
    "speed": 130.0,
    "behavior_type": "seek_center",
    "sprite_scale": 0.24,
    "sprite_tint": [0.96, 0.74, 0.28, 1.0],
    "collision_radius": 18.0,
    "idle_time_range": [0.35, 0.8],
    "walk_time_range": [0.28, 0.52]
  }
]
